tests/__init__.py
tests/test_SlurmManager.py
SlurmManager-0.1.dist-info/METADATA
SlurmManager-0.1.dist-info/WHEEL
SlurmManager-0.1.dist-info/top_level.txt
SlurmManager-0.1.dist-info/RECORD
