Metadata-Version: 2.1
Name: SlurmManager
Version: 0.1
Summary: A Python module to manage SLURM jobs.
Author: Lukas
Author-email: lherron@umd.edu
Classifier: Programming Language :: Python :: 3
Classifier: License :: OSI Approved :: MIT License
Classifier: Operating System :: OS Independent
Requires-Python: >=3.6
